uif_client/.main.py.un~
uif_client/__init__.py
uif_client/__main__.py
uif_client/main.py
uif_client/__pycache__/__init__.cpython-39.pyc
uif_client/__pycache__/main.cpython-39.pyc
uif_client/caddy_config/caddy_config.json
uif_client/caddy_config/caddy_config2.json
uif_client/caddy_config/not_safe.txt
uif_client/caddy_config/safe.txt
uif_client/caddy_config/tls_ws.txt
uif_client/caddy_config/tls_ws_with_free.txt
uif_client/caddy_config/using.caddyfile
uif_client/ctrl/client_debug.log
uif_client/ctrl/deamon.py
uif_client/ctrl/linux_x64.exe
uif_client/ctrl/windows_x64.exe
uif_client/ctrl/contro/go.mod
uif_client/ctrl/contro/go.sum
uif_client/ctrl/contro/main.go
uif_client/v2ray_config/.rrs_config.json.un~
uif_client/v2ray_config/RRS_Linux.exe
uif_client/v2ray_config/default.json
uif_client/v2ray_config/default_in.json
uif_client/v2ray_config/not_safe.json
uif_client/v2ray_config/rrs_config.json
uif_client/v2ray_config/vmess_tls_ws.json
uif_client/v2ray_config/vmess_tls_ws_free.json
uif_client/v2ray_config/vmess_tls_ws_free_ipv6.json
uif_client/v2ray_config/vmess_tls_ws_ipv6.json
abc_0329-1687508180.dist-info/METADATA
abc_0329-1687508180.dist-info/WHEEL
abc_0329-1687508180.dist-info/top_level.txt
abc_0329-1687508180.dist-info/RECORD
